src/net_van/__init__.py
src/net_van/Learn_network.py
src/net_van/Network.py
net_van-0.1.1.dist-info/LICENSE
net_van-0.1.1.dist-info/METADATA
net_van-0.1.1.dist-info/WHEEL
net_van-0.1.1.dist-info/RECORD
